paradigm_client/__init__.py
paradigm_client/communicator.py
paradigm_client/remote_model.py
paradigm_client/request.py
paradigm_client/response.py
paradigm_client/wrappers/__init__.py
paradigm_client/wrappers/langchain.py
paradigm_client/wrappers/llama_index.py
paradigm_client-0.5.2.dist-info/LICENSE
paradigm_client-0.5.2.dist-info/METADATA
paradigm_client-0.5.2.dist-info/WHEEL
paradigm_client-0.5.2.dist-info/top_level.txt
paradigm_client-0.5.2.dist-info/RECORD
