Metadata-Version: 2.1
Name: paradigm-client
Version: 0.5.2
Summary: Python client for LightOn Paradigm
Home-page: https://github.com/lightonai/paradigm-client
Author: LightOn AI
Author-email: support@lighton.ai
Keywords: NLP,API,AI,LLM
Classifier: Programming Language :: Python
Classifier: Programming Language :: Python :: 3
Classifier: Programming Language :: Python :: 3.10
Classifier: Topic :: Scientific/Engineering :: Artificial Intelligence
Classifier: Development Status :: 4 - Beta
Classifier: Intended Audience :: Science/Research
Classifier: License :: OSI Approved :: MIT License
License-File: LICENSE
Requires-Dist: aiohttp >=3.8.4
Requires-Dist: pydantic ==1.10.2
Requires-Dist: requests >=2.31.0
Requires-Dist: tqdm >=4.64.1
Provides-Extra: langchain
Requires-Dist: langchain >=0.0.306 ; extra == 'langchain'
Provides-Extra: sagemaker
Requires-Dist: boto3 >=1.28.66 ; extra == 'sagemaker'
Requires-Dist: botocore >=1.31.66 ; extra == 'sagemaker'
